braid/__init__.py
braid/berry/__init__.py
braid/berry/activations.py
braid/berry/base.py
braid/berry/config.py
braid/berry/initializations.py
braid/berry/objectives.py
braid/berry/optimizers.py
braid/berry/utils.py
braid/berry/layers/__init__.py
braid/berry/layers/base.py
braid/berry/layers/convolution.py
braid/berry/layers/dense.py
braid/berry/layers/noise.py
braid/berry/layers/pooling.py
braid/berry/layers/shape.py
braid/berryflow/__init__.py
braid/berryflow/base.py
braid/berryflow/data_manager/__init__.py
braid/berryflow/data_manager/lmdb_generator.py
braid/berryflow/data_manager/preprocessing.py
braid/berryflow/data_manager/transformer.py
braid/berryflow/data_manager/vanilla_generator.py
braid/berryflow/misc/__init__.py
braid/berryflow/misc/config.py
braid/berryflow/misc/utils.py
braid/berryflow/models/__init__.py
braid/berryflow/models/alexnet.py
braid/berryflow/models/lenet.py
braid/berryflow/models/vgg.py
braid/berryflow/outputs/__init__.py
braid/berryflow/outputs/custom_callback.py
braid/berryflow/proto/__init__.py
braid/berryflow/proto/datum_pb2.py
braid/protoflow/__init__.py
braid/protoflow/base.py
braid/protoflow/proto/__init__.py
braid/protoflow/proto/berry_pb2.py
braid-0.1.dist-info/DESCRIPTION.rst
braid-0.1.dist-info/METADATA
braid-0.1.dist-info/RECORD
braid-0.1.dist-info/WHEEL
braid-0.1.dist-info/metadata.json
braid-0.1.dist-info/top_level.txt
